neaky.cp37-win_amd64.pyd
neaky-1.0.0.dist-info/METADATA
neaky-1.0.0.dist-info/WHEEL
neaky-1.0.0.dist-info/top_level.txt
neaky-1.0.0.dist-info/RECORD
