Metadata-Version: 2.1
Name: neaky
Version: 1.0.0
Summary: A python native module providing some spyware function on Windows.
Home-page: https://github.com/am009/pyneaky
Author: Warren Wang
Author-email: warrenwjk@gmail.com
License: MIT
Platform: UNKNOWN
Classifier: License :: OSI Approved :: MIT License
Classifier: Programming Language :: Python :: 3
Classifier: Programming Language :: Python :: 3.7
Requires-Python: >=3.4
